recaptcha3/__init__.py
recaptcha3/exceptions.py
recaptcha3/session.py
recaptcha3/structs.py
recaptcha3/utils.py
recaptcha3/reCaptchaV3/__init__.py
recaptcha3/reCaptchaV3/constants.py
RecaptchaV3-1.dist-info/LICENSE
RecaptchaV3-1.dist-info/METADATA
RecaptchaV3-1.dist-info/WHEEL
RecaptchaV3-1.dist-info/top_level.txt
RecaptchaV3-1.dist-info/RECORD
